{
  "left baffle": [
    [
      694,
      229
    ],
    [
      685,
      269
    ],
    [
      634,
      257
    ],
    [
      619,
      285
    ],
    [
      582,
      484
    ],
    [
      581,
      575
    ],
    [
      594,
      618
    ],
    [
      610,
      619
    ],
    [
      618,
      606
    ],
    [
      616,
      552
    ],
    [
      640,
      384
    ],
    [
      648,
      362
    ],
    [
      693,
      314
    ]
  ],
  "right baffle": [
    [
      776,
      231
    ],
    [
      773,
      258
    ],
    [
      784,
      319
    ],
    [
      857,
      360
    ],
    [
      868,
      376
    ],
    [
      907,
      556
    ],
    [
      900,
      594
    ],
    [
      913,
      618
    ],
    [
      935,
      616
    ],
    [
      954,
      562
    ],
    [
      954,
      471
    ],
    [
      902,
      295
    ],
    [
      886,
      266
    ],
    [
      871,
      258
    ],
    [
      787,
      272
    ]
  ],
  "step": [
    [
      706,
      309
    ],
    [
      701,
      334
    ],
    [
      674,
      384
    ],
    [
      652,
      530
    ],
    [
      863,
      531
    ],
    [
      838,
      405
    ],
    [
      826,
      385
    ],
    [
      773,
      334
    ],
    [
      765,
      310
    ]
  ],
  "floor plate": [
    [
      564,
      665
    ],
    [
      562,
      719
    ],
    [
      951,
      719
    ],
    [
      936,
      620
    ],
    [
      913,
      619
    ],
    [
      902,
      602
    ],
    [
      873,
      597
    ],
    [
      863,
      532
    ],
    [
      653,
      532
    ],
    [
      643,
      599
    ],
    [
      622,
      602
    ],
    [
      610,
      620
    ],
    [
      594,
      619
    ],
    [
      581,
      606
    ]
  ],
  "large_step": [
    [
      693,
      309
    ],
    [
      674,
      334
    ],
    [
      640,
      384
    ],
    [
      619,
      530
    ],
    [
      902,
      531
    ],
    [
      874,
      405
    ],
    [
      870,
      385
    ],
    [
      811,
      334
    ],
    [
      782,
      310
    ]
  ],
  "larger_step": [
    [
      615,
      309
    ],
    [
      610,
      334
    ],
    [
      601,
      384
    ],
    [
      581,
      530
    ],
    [
      954,
      531
    ],
    [
      934,
      405
    ],
    [
      929,
      385
    ],
    [
      914,
      334
    ],
    [
      906,
      310
    ]
  ],
  "imgHeight": 720,
  "imgWidth": 1280
}